fairchild/__init__.py
fairchild/cli.py
fairchild/context.py
fairchild/fairchild.py
fairchild/future.py
fairchild/job.py
fairchild/record.py
fairchild/task.py
fairchild/ui.py
fairchild/worker.py
fairchild/db/__init__.py
fairchild/db/migrations.py
fairchild/db/migrations/001_initial.sql
fairchild/db/migrations/002_add_parent_id.sql
fairchild/db/migrations/003_remove_workflows.sql
fairchild/db/migrations/004_add_workers.sql
fairchild/db/migrations/005_add_worker_tasks.sql
fairchild/templates/dashboard.html
fairchild/templates/job.html
fairchild-0.0.5.dist-info/licenses/LICENSE
fairchild-0.0.5.dist-info/METADATA
fairchild-0.0.5.dist-info/WHEEL
fairchild-0.0.5.dist-info/entry_points.txt
fairchild-0.0.5.dist-info/top_level.txt
fairchild-0.0.5.dist-info/RECORD
