Metadata-Version: 2.4
Name: fairchild
Version: 0.0.5
Summary: Workflow scheduling with PostgreSQL
Requires-Python: >=3.13
License-File: LICENSE
Requires-Dist: asyncpg>=0.29.0
Requires-Dist: click>=8.0.0
Requires-Dist: aiohttp>=3.9.0
Provides-Extra: dev
Requires-Dist: pytest>=8.0.0; extra == "dev"
Requires-Dist: pytest-asyncio>=0.23.0; extra == "dev"
Dynamic: license-file
